README.txt
setup.py
docs/HISTORY.txt
docs/INSTALL.txt
docs/LICENSE.GPL
docs/LICENSE.txt
wildcard/__init__.py
wildcard.lockdown.egg-info/PKG-INFO
wildcard.lockdown.egg-info/SOURCES.txt
wildcard.lockdown.egg-info/dependency_links.txt
wildcard.lockdown.egg-info/entry_points.txt
wildcard.lockdown.egg-info/namespace_packages.txt
wildcard.lockdown.egg-info/not-zip-safe
wildcard.lockdown.egg-info/requires.txt
wildcard.lockdown.egg-info/top_level.txt
wildcard/lockdown/__init__.py
wildcard/lockdown/configure.zcml
wildcard/lockdown/controlpanel.py
wildcard/lockdown/events.py
wildcard/lockdown/interfaces.py
wildcard/lockdown/lockdown.png
wildcard/lockdown/testing.py
wildcard/lockdown/Extensions/Install.py
wildcard/lockdown/profiles/default/browserlayer.xml
wildcard/lockdown/profiles/default/controlpanel.xml
wildcard/lockdown/profiles/default/metadata.xml
wildcard/lockdown/profiles/default/registry.xml
wildcard/lockdown/profiles/uninstall/controlpanel.xml
wildcard/lockdown/tests/__init__.py
wildcard/lockdown/tests/test_conditions.py
wildcard/lockdown/tests/test_lockdown.py
wildcard/lockdown/tests/test_registry.py