Metadata-Version: 1.0
Name: wildcard.lockdown
Version: 1.0a1
Summary: UNKNOWN
Home-page: http://svn.plone.org/svn/collective/
Author: UNKNOWN
Author-email: UNKNOWN
License: GPL
Platform: UNKNOWN
Classifier: Framework :: Plone
Classifier: Programming Language :: Python
